schemic/__init__.py
schemic-1.1.0.dist-info/licenses/LICENSE
schemic-1.1.0.dist-info/METADATA
schemic-1.1.0.dist-info/WHEEL
schemic-1.1.0.dist-info/top_level.txt
schemic-1.1.0.dist-info/RECORD
