Metadata-Version: 2.4
Name: schemic
Version: 1.1.0
Summary: Simplify using Pydantic models with LLMs in a type-safe way
Home-page: https://github.com/reedgraff/schemic
Author: Reed Graff
Author-email: rangergraff@gmail.com
Classifier: Programming Language :: Python :: 3
Classifier: License :: OSI Approved :: MIT License
Classifier: Operating System :: OS Independent
Requires-Python: >=3.8
License-File: LICENSE
Requires-Dist: pydantic>=2.0.0
Dynamic: author
Dynamic: author-email
Dynamic: classifier
Dynamic: description
Dynamic: description-content-type
Dynamic: home-page
Dynamic: license-file
Dynamic: requires-dist
Dynamic: requires-python
Dynamic: summary
